detest/ConvergenceTest.py
detest/ExactTest.py
detest/TestRunner.py
detest/TestingSuite.py
detest/__init__.py
detest/vtkutil.py
detest/oracles/__init__.py
detest/oracles/deLeeuw.py
detest/oracles/heat_equation.py
detest/oracles/heat_equation_1d.py
detest/oracles/mechanics_constant.py
detest/oracles/nonlinear_pendulum.py
detest/oracles/odes.py
detest/oracles/poisson_equation_1d.py
detest/oracles/poroelastic_constant.py
detest/oracles/poroelastic_well.py
detest/oracles/single_phase_well.py
detest/oracles/square_poisson.py
detest/oracles/terzaghi.py
detest/oracles/thin_crack.py
detest/oracles/wave_equation_1d.py
detest-0.2.dist-info/LICENSE.txt
detest-0.2.dist-info/METADATA
detest-0.2.dist-info/WHEEL
detest-0.2.dist-info/top_level.txt
detest-0.2.dist-info/RECORD
