Metadata-Version: 2.1
Name: detest
Version: 0.2
Summary: A differential equation testing suite
Home-page: https://github.com/afqueiruga/detest
Author: Alejandro Francisco Queiruga
License: GNU LGPL
Platform: UNKNOWN
